modguard/__init__.py
modguard/boundary.py
modguard/check.py
modguard/cli.py
modguard/colors.py
modguard/errors.py
modguard/init.py
modguard/loading.py
modguard/public.py
modguard/show.py
modguard/core/__init__.py
modguard/core/boundary.py
modguard/core/public.py
modguard/filesystem/__init__.py
modguard/filesystem/service.py
modguard/parsing/__init__.py
modguard/parsing/ast_visitor.py
modguard/parsing/boundary.py
modguard/parsing/imports.py
modguard/parsing/public.py
modguard-0.7.1.dist-info/LICENSE
modguard-0.7.1.dist-info/METADATA
modguard-0.7.1.dist-info/WHEEL
modguard-0.7.1.dist-info/entry_points.txt
modguard-0.7.1.dist-info/top_level.txt
modguard-0.7.1.dist-info/RECORD
